[{
	"img": "img/首页/Zero65.jpg",
	"name": "Zero65"
}, {
	"img": "img/首页/X65L.jpg",
	"name": "X65L"
}, {
	"img": "img/首页/X65S.jpg",
	"name": "X65S"
}, {
	"img": "img/首页/X55C.jpg",
	"name": "X55C"
},{
	"img": "img/首页/X50Pro.jpg",
	"name": "X50 Pro"
}, {
	"img": "img/首页/X55L.jpg",
	"name": "X55L"
}, {
	"img": "img/首页/X55C.jpg",
	"name": "X55C"
}, {
	"img": "img/首页/X40C.jpg",
	"name": "X40C"
}, {
	"img": "img/首页/X40L.jpg",
	"name": "X40L"
}, {
	"img": "img/首页/uMax85.jpg",
	"name": "uMax85"
}, {
	"img": "img/首页/Unique75s.jpg",
	"name": "Unique75s"
}, {
	"img": "img/首页/Zero65.jpg",
	"name": "Zero65"
}]
